README.md
setup.py
propobject/__init__.py
propobject/baseobject.py
propobject.egg-info/PKG-INFO
propobject.egg-info/SOURCES.txt
propobject.egg-info/dependency_links.txt
propobject.egg-info/top_level.txt