Metadata-Version: 1.1
Name: propobject
Version: 0.1.2
Summary: propobject: Low level object to inherit from
Home-page: https://github.com/MickaelRigault/propobject/
Author: Mickael Rigault
Author-email: mrigault@physik.hu-berlin.de
License: Apache 2.0
Download-URL: https://github.com/MickaelRigault/propobject/tarball/0.1
Platform: UNKNOWN
Classifier: Intended Audience :: Science/Research
Classifier: Programming Language :: Python :: 2.7
Classifier: Programming Language :: Python :: 3.5
Classifier: License :: OSI Approved :: BSD License
Classifier: Topic :: Scientific/Engineering :: Astronomy
Classifier: Operating System :: POSIX
Classifier: Operating System :: Unix
Classifier: Operating System :: MacOS
